xeet/__init__.py
xeet/__main__.py
xeet/_version.py
xeet/cli.py
xeet/cli_printer.py
xeet/common.py
xeet/log.py
xeet/pr.py
xeet/core/__init__.py
xeet/core/api.py
xeet/core/driver.py
xeet/core/event_logger.py
xeet/core/events.py
xeet/core/matrix.py
xeet/core/resource.py
xeet/core/result.py
xeet/core/step.py
xeet/core/test.py
xeet/core/test_runner.py
xeet/steps/__init__.py
xeet/steps/dummy_step.py
xeet/steps/exec_step.py
xeet-0.7.0.post12.dist-info/licenses/LICENSE
xeet-0.7.0.post12.dist-info/METADATA
xeet-0.7.0.post12.dist-info/WHEEL
xeet-0.7.0.post12.dist-info/entry_points.txt
xeet-0.7.0.post12.dist-info/top_level.txt
xeet-0.7.0.post12.dist-info/RECORD
